lightning_cv/__init__.py
lightning_cv/__metadata__.py
lightning_cv/_optional.py
lightning_cv/config.py
lightning_cv/data.py
lightning_cv/fabric.py
lightning_cv/py.typed
lightning_cv/split.py
lightning_cv/trainer.py
lightning_cv/callbacks/__init__.py
lightning_cv/callbacks/base.py
lightning_cv/callbacks/checkpoint.py
lightning_cv/callbacks/logger.py
lightning_cv/callbacks/lr_monitor.py
lightning_cv/callbacks/mode.py
lightning_cv/callbacks/perf_monitor.py
lightning_cv/callbacks/progress.py
lightning_cv/callbacks/stopping.py
lightning_cv/callbacks/summary.py
lightning_cv/callbacks/timer.py
lightning_cv/callbacks/utils.py
lightning_cv/tuning/__init__.py
lightning_cv/tuning/callbacks.py
lightning_cv/tuning/config.py
lightning_cv/tuning/hyperparameters.py
lightning_cv/tuning/tuner.py
lightning_cv/tuning/utils.py
lightning_cv/typehints/__init__.py
lightning_cv/typehints/config.py
lightning_cv/typehints/data.py
lightning_cv/typehints/module.py
lightning_cv/typehints/split.py
lightning_cv/utils/__init__.py
lightning_cv/utils/checkpointing.py
lightning_cv/utils/dataclasses.py
lightning_cv/utils/foldutils.py
lightning_cv/utils/serde.py
lightning_cv/utils/stopping.py
lightning_cv/utils/strategies.py
lightning_cv/utils/validators.py
lightning_cv-1.1.0.dist-info/licenses/LICENSE
lightning_cv-1.1.0.dist-info/METADATA
lightning_cv-1.1.0.dist-info/WHEEL
lightning_cv-1.1.0.dist-info/top_level.txt
lightning_cv-1.1.0.dist-info/RECORD
