Metadata-Version: 2.4
Name: lightning-cv
Version: 1.1.0
Summary: Cross validation using Lightning Fabric
Author-email: Cody Martin <codycmar10@gmail.com>
License: MIT License
Project-URL: Homepage, https://github.com/cody-mar10/lightning-crossval
Project-URL: Bug Tracker, https://github.com/cody-mar10/lightning-crossval/issues
Classifier: Programming Language :: Python :: 3
Classifier: License :: OSI Approved :: MIT License
Requires-Python: >=3.9
License-File: LICENSE
Requires-Dist: torch>=2
Requires-Dist: lightning>=2
Requires-Dist: boltons
Requires-Dist: attrs>=24.2
Requires-Dist: cattrs>=24.1
Provides-Extra: tune
Requires-Dist: optuna>=3.1; extra == "tune"
Requires-Dist: tomli; python_version < "3.11" and extra == "tune"
Provides-Extra: test
Requires-Dist: pytest>=8.3; extra == "test"
Requires-Dist: pytest-cov; extra == "test"
Requires-Dist: scikit-learn; extra == "test"
Provides-Extra: build
Requires-Dist: ruff; extra == "build"
Requires-Dist: mypy; extra == "build"
Requires-Dist: isort; extra == "build"
Requires-Dist: covdefaults; extra == "build"
Provides-Extra: dev
Requires-Dist: lightning-cv[build]; extra == "dev"
Requires-Dist: lightning-cv[test]; extra == "dev"
Dynamic: license-file
